aio_windows_patch/__init__.py
aio_windows_patch/base_events.py
aio_windows_patch/base_futures.py
aio_windows_patch/base_subprocess.py
aio_windows_patch/base_tasks.py
aio_windows_patch/compat.py
aio_windows_patch/constants.py
aio_windows_patch/coroutines.py
aio_windows_patch/events.py
aio_windows_patch/futures.py
aio_windows_patch/locks.py
aio_windows_patch/log.py
aio_windows_patch/proactor_events.py
aio_windows_patch/protocols.py
aio_windows_patch/queues.py
aio_windows_patch/selector_events.py
aio_windows_patch/sslproto.py
aio_windows_patch/streams.py
aio_windows_patch/subprocess.py
aio_windows_patch/tasks.py
aio_windows_patch/test_utils.py
aio_windows_patch/transports.py
aio_windows_patch/unix_events.py
aio_windows_patch/windows_events.py
aio_windows_patch/windows_utils.py
aio_windows_patch-0.0.1.data/data/requirements/requirements.txt
aio_windows_patch-0.0.1.data/data/requirements/requirements_dev.txt
aio_windows_patch-0.0.1.data/data/requirements/requirements_test.txt
aio_windows_patch-0.0.1.dist-info/DESCRIPTION.rst
aio_windows_patch-0.0.1.dist-info/METADATA
aio_windows_patch-0.0.1.dist-info/RECORD
aio_windows_patch-0.0.1.dist-info/WHEEL
aio_windows_patch-0.0.1.dist-info/metadata.json
aio_windows_patch-0.0.1.dist-info/top_level.txt
