Metadata-Version: 2.0
Name: aio-windows-patch
Version: 0.0.1
Summary: simple tools
Home-page: https://github.com/Python-Tools/aio_windows_patch
Author: hsz
Author-email: hsz1273327@gmail.com
License: MIT
Provides-Extra: dev
Requires-Dist: wheel; extra == 'dev'
Provides-Extra: test
Requires-Dist: coverage; extra == 'test'
Requires-Dist: mypy; extra == 'test'
Requires-Dist: mypy-extensions; extra == 'test'
Requires-Dist: lxml; extra == 'test'
